unitclass.py
unitclass-1.1.1.dist-info/LICENSE
unitclass-1.1.1.dist-info/METADATA
unitclass-1.1.1.dist-info/WHEEL
unitclass-1.1.1.dist-info/top_level.txt
unitclass-1.1.1.dist-info/RECORD
