Metadata-Version: 2.1
Name: unitclass
Version: 1.1.1
Summary: Physical unit class suitable for calculations in the sciences.
Author-email: Blake Garretson <blake@blakeg.net>
Project-URL: Homepage, https://github.com/blakegarretson/unitclass
Project-URL: Bug Tracker, https://github.com/blakegarretson/unitclass/issues
Keywords: unit,units,SI,conversion
Classifier: Programming Language :: Python :: 3
Classifier: License :: OSI Approved :: GNU General Public License v3 (GPLv3)
Classifier: Operating System :: OS Independent
Classifier: Topic :: Scientific/Engineering
Classifier: Topic :: Scientific/Engineering :: Physics
Classifier: Topic :: Scientific/Engineering :: Mathematics
Requires-Python: >=3.8
License-File: LICENSE
